{"id": "https://openalex.org/W4283718955", "doi": "https://doi.org/10.48550/arxiv.2206.13813", "title": "Sublinear-Time Clustering Oracle for Signed Graphs", "display_name": "Sublinear-Time Clustering Oracle for Signed Graphs", "publication_year": 2022, "publication_date": "2022-01-01", "ids": {"openalex": "https://openalex.org/W4283718955", "doi": "https://doi.org/10.48550/arxiv.2206.13813"}, "language": "en", "primary_location": {"is_oa": true, "landing_page_url": "https://arxiv.org/abs/2206.13813", "pdf_url": null, "source": {"id": "https://openalex.org/S4306400194", "display_name": "arXiv (Cornell University)", "issn_l": null, "issn": null, "is_oa": true, "is_in_doaj": false, "host_organization": "https://openalex.org/I205783295", "host_organization_name": "Cornell University", "host_organization_lineage": ["https://openalex.org/I205783295"], "host_organization_lineage_names": ["Cornell University"], "type": "repository"}, "license": "arXiv.org perpetual, non-exclusive license", "license_id": "https://openalex.org/licenses/other-oa", "version": "submittedVersion", "is_accepted": false, "is_published": false}, "type": "preprint", "type_crossref": "posted-content", "indexed_in": ["arxiv", "datacite"], "open_access": {"is_oa": true, "oa_status": "green", "oa_url": "https://arxiv.org/abs/2206.13813", "any_repository_has_fulltext": true}, "authorships": [{"author_position": "first", "author": {"id": "https://openalex.org/A5008120721", "display_name": "Stefan Neumann", "orcid": "https://orcid.org/0000-0002-3981-1500"}, "institutions": [], "countries": [], "is_corresponding": false, "raw_author_name": "Neumann, Stefan", "raw_affiliation_strings": []}, {"author_position": "last", "author": {"id": "https://openalex.org/A5039636218", "display_name": "Peng Pan", "orcid": "https://orcid.org/0000-0001-5723-6477"}, "institutions": [], "countries": [], "is_corresponding": false, "raw_author_name": "Peng, Pan", "raw_affiliation_strings": []}], "countries_distinct_count": 0, "institutions_distinct_count": 0, "corresponding_author_ids": [], "corresponding_institution_ids": [], "apc_list": null, "apc_paid": null, "has_fulltext": false, "cited_by_count": 0, "cited_by_percentile_year": {"min": 0, "max": 67}, "biblio": {"volume": null, "issue": null, "first_page": null, "last_page": null}, "is_retracted": false, "is_paratext": false, "primary_topic": {"id": "https://openalex.org/T10064", "display_name": "Statistical Mechanics of Complex Networks", "score": 0.9995, "subfield": {"id": "https://openalex.org/subfields/3109", "display_name": "Statistical and Nonlinear Physics"}, "field": {"id": "https://openalex.org/fields/31", "display_name": "Physics and Astronomy"}, "domain": {"id": "https://openalex.org/domains/3", "display_name": "Physical Sciences"}}, "topics": [{"id": "https://openalex.org/T10064", "display_name": "Statistical Mechanics of Complex Networks", "score": 0.9995, "subfield": {"id": "https://openalex.org/subfields/3109", "display_name": "Statistical and Nonlinear Physics"}, "field": {"id": "https://openalex.org/fields/31", "display_name": "Physics and Astronomy"}, "domain": {"id": "https://openalex.org/domains/3", "display_name": "Physical Sciences"}}, {"id": "https://openalex.org/T11273", "display_name": "Graph Neural Network Models and Applications", "score": 0.995, "subfield": {"id": "https://openalex.org/subfields/1702", "display_name": "Artificial Intelligence"}, "field": {"id": "https://openalex.org/fields/17", "display_name": "Computer Science"}, "domain": {"id": "https://openalex.org/domains/3", "display_name": "Physical Sciences"}}, {"id": "https://openalex.org/T11478", "display_name": "Content-Centric Networking for Information Delivery", "score": 0.9935, "subfield": {"id": "https://openalex.org/subfields/1705", "display_name": "Computer Networks and Communications"}, "field": {"id": "https://openalex.org/fields/17", "display_name": "Computer Science"}, "domain": {"id": "https://openalex.org/domains/3", "display_name": "Physical Sciences"}}], "keywords": [{"id": "https://openalex.org/keywords/signal-processing-on-graphs", "display_name": "Signal Processing on Graphs", "score": 0.558988}, {"id": "https://openalex.org/keywords/community-structure", "display_name": "Community Structure", "score": 0.557129}, {"id": "https://openalex.org/keywords/named-data-networking", "display_name": "Named Data Networking", "score": 0.51231}, {"id": "https://openalex.org/keywords/knowledge-graph-embedding", "display_name": "Knowledge Graph Embedding", "score": 0.511053}, {"id": "https://openalex.org/keywords/network-embedding", "display_name": "Network Embedding", "score": 0.507403}], "concepts": [{"id": "https://openalex.org/C114614502", "wikidata": "https://www.wikidata.org/wiki/Q76592", "display_name": "Combinatorics", "level": 1, "score": 0.7204213}, {"id": "https://openalex.org/C80899671", "wikidata": "https://www.wikidata.org/wiki/Q1304193", "display_name": "Vertex (graph theory)", "level": 3, "score": 0.5932257}, {"id": "https://openalex.org/C55166926", "wikidata": "https://www.wikidata.org/wiki/Q2892946", "display_name": "Oracle", "level": 2, "score": 0.5324059}, {"id": "https://openalex.org/C73555534", "wikidata": "https://www.wikidata.org/wiki/Q622825", "display_name": "Cluster analysis", "level": 2, "score": 0.51804733}, {"id": "https://openalex.org/C117160843", "wikidata": "https://www.wikidata.org/wiki/Q338652", "display_name": "Sublinear function", "level": 2, "score": 0.49709943}, {"id": "https://openalex.org/C34388435", "wikidata": "https://www.wikidata.org/wiki/Q2267362", "display_name": "Bounded function", "level": 2, "score": 0.49443936}, {"id": "https://openalex.org/C33923547", "wikidata": "https://www.wikidata.org/wiki/Q395", "display_name": "Mathematics", "level": 0, "score": 0.46741796}, {"id": "https://openalex.org/C118615104", "wikidata": "https://www.wikidata.org/wiki/Q121416", "display_name": "Discrete mathematics", "level": 1, "score": 0.46611458}, {"id": "https://openalex.org/C132525143", "wikidata": "https://www.wikidata.org/wiki/Q141488", "display_name": "Graph", "level": 2, "score": 0.3537236}, {"id": "https://openalex.org/C41008148", "wikidata": "https://www.wikidata.org/wiki/Q21198", "display_name": "Computer science", "level": 0, "score": 0.35118178}, {"id": "https://openalex.org/C154945302", "wikidata": "https://www.wikidata.org/wiki/Q11660", "display_name": "Artificial intelligence", "level": 1, "score": 0.12784833}, {"id": "https://openalex.org/C134306372", "wikidata": "https://www.wikidata.org/wiki/Q7754", "display_name": "Mathematical analysis", "level": 1, "score": 0.0}, {"id": "https://openalex.org/C115903868", "wikidata": "https://www.wikidata.org/wiki/Q80993", "display_name": "Software engineering", "level": 1, "score": 0.0}], "mesh": [], "locations_count": 2, "locations": [{"is_oa": true, "landing_page_url": "https://arxiv.org/abs/2206.13813", "pdf_url": null, "source": {"id": "https://openalex.org/S4306400194", "display_name": "arXiv (Cornell University)", "issn_l": null, "issn": null, "is_oa": true, "is_in_doaj": false, "host_organization": "https://openalex.org/I205783295", "host_organization_name": "Cornell University", "host_organization_lineage": ["https://openalex.org/I205783295"], "host_organization_lineage_names": ["Cornell University"], "type": "repository"}, "license": "arXiv.org perpetual, non-exclusive license", "license_id": "https://openalex.org/licenses/other-oa", "version": "submittedVersion", "is_accepted": false, "is_published": false}, {"is_oa": false, "landing_page_url": "https://api.datacite.org/dois/10.48550/arxiv.2206.13813", "pdf_url": null, "source": {"id": "https://openalex.org/S4393179698", "display_name": "DataCite API", "issn_l": null, "issn": null, "is_oa": true, "is_in_doaj": false, "host_organization": "https://openalex.org/I4210145204", "host_organization_name": "DataCite", "host_organization_lineage": ["https://openalex.org/I4210145204"], "host_organization_lineage_names": ["DataCite"], "type": "metadata"}, "license": null, "license_id": null, "version": null}], "best_oa_location": {"is_oa": true, "landing_page_url": "https://arxiv.org/abs/2206.13813", "pdf_url": null, "source": {"id": "https://openalex.org/S4306400194", "display_name": "arXiv (Cornell University)", "issn_l": null, "issn": null, "is_oa": true, "is_in_doaj": false, "host_organization": "https://openalex.org/I205783295", "host_organization_name": "Cornell University", "host_organization_lineage": ["https://openalex.org/I205783295"], "host_organization_lineage_names": ["Cornell University"], "type": "repository"}, "license": "arXiv.org perpetual, non-exclusive license", "license_id": "https://openalex.org/licenses/other-oa", "version": "submittedVersion", "is_accepted": false, "is_published": false}, "sustainable_development_goals": [], "grants": [], "datasets": [], "versions": [], "referenced_works_count": 0, "referenced_works": [], "related_works": ["https://openalex.org/W90906771", "https://openalex.org/W2018828772", "https://openalex.org/W2529185025", "https://openalex.org/W2052708136", "https://openalex.org/W2809723425", "https://openalex.org/W4289097813", "https://openalex.org/W3082028334", "https://openalex.org/W2005302727", "https://openalex.org/W1973725449", "https://openalex.org/W2891477601"], "ngrams_url": "https://api.openalex.org/works/W4283718955/ngrams", "abstract_inverted_index": {"Social": [0], "networks": [1], "are": [2], "often": [3], "modeled": [4], "using": [5], "signed": [6, 31, 73, 191], "graphs,": [7], "where": [8, 164], "vertices": [9, 149], "correspond": [10], "to": [11, 190], "users": [12, 24], "and": [13, 60, 117, 142, 199, 222, 229], "edges": [14], "have": [15], "a": [16, 35, 49, 57, 68, 77, 88, 103, 146, 151, 172, 194, 201], "sign": [17], "that": [18, 42, 81], "indicates": [19], "whether": [20], "an": [21, 220], "interaction": [22], "between": [23], "was": [25], "positive": [26], "or": [27], "negative.": [28], "The": [29], "arising": [30], "graphs": [32, 74, 192], "typically": [33], "contain": [34], "clear": [36, 78], "community": [37, 79, 92], "structure": [38], "in": [39, 97, 139, 162, 235], "the": [40, 43, 107, 111, 118, 165, 206], "sense": [41], "graph": [44, 112], "can": [45, 82, 134], "be": [46], "partitioned": [47], "into": [48, 62], "small": [50, 104, 173], "number": [51, 119, 174, 195], "of": [52, 106, 120, 148, 153, 175, 196, 205, 208], "polarized": [53, 64], "communities,": [54], "each": [55, 136], "defining": [56], "sparse": [58], "cut": [59], "indivisible": [61], "smaller": [63], "sub-communities.": [65], "We": [66, 213], "provide": [67], "local": [69, 179], "clustering": [70, 166, 180], "oracle": [71, 133, 159, 221], "for": [72, 170, 185, 217], "with": [75, 128, 211], "such": [76, 178, 219], "structure,": [80], "answer": [83, 135], "membership": [84, 137, 224], "queries,": [85], "i.e.,": [86], "\"Given": [87], "vertex": [89], "$v$,": [90], "which": [91], "does": [93], "$v$": [94], "belong": [95], "to?\",": [96], "sublinear": [98], "time": [99], "by": [100], "reading": [101], "only": [102, 171, 183], "portion": [105], "graph.": [108], "Formally,": [109], "when": [110], "has": [113], "bounded": [114], "maximum": [115], "degree": [116], "communities": [121], "is": [122, 160, 168], "at": [123], "most": [124], "$O(\\log": [125], "n)$,": [126], "then": [127], "$\\tilde{O}(\\sqrt{n}\\operatorname{poly}(1/\\varepsilon))$": [129, 140], "preprocessing": [130], "time,": [131, 141], "our": [132, 188, 215], "query": [138], "it": [143], "correctly": [144], "classifies": [145], "$(1-\\varepsilon)$-fraction": [147], "w.r.t.": [150], "set": [152], "hidden": [154], "planted": [155], "ground-truth": [156], "communities.": [157], "Our": [158], "desirable": [161], "applications": [163], "information": [167], "needed": [169], "vertices.": [176], "Previously,": [177], "oracles": [181], "were": [182], "known": [184], "unsigned": [186], "graphs;": [187], "generalization": [189], "requires": [193], "new": [197], "ideas": [198], "gives": [200], "novel": [202], "spectral": [203], "analysis": [204], "behavior": [207], "random": [209], "walks": [210], "signs.": [212], "evaluate": [214], "algorithm": [216], "constructing": [218], "answering": [223], "queries": [225], "on": [226], "both": [227], "synthetic": [228], "real-world": [230], "datasets,": [231], "validating": [232], "its": [233], "performance": [234], "practice.": [236]}, "cited_by_api_url": "https://api.openalex.org/works?filter=cites:W4283718955", "counts_by_year": [], "updated_date": "2024-04-28T01:22:59.733985", "created_date": "2022-07-01"}