{"id": "https://openalex.org/W2752086744", "doi": null, "title": "Excess Risk Bounds for the Bayes Risk using Variational Inference in Latent Gaussian Models", "display_name": "Excess Risk Bounds for the Bayes Risk using Variational Inference in Latent Gaussian Models", "publication_year": 2017, "publication_date": "2017-01-01", "ids": {"openalex": "https://openalex.org/W2752086744", "mag": "2752086744"}, "language": "en", "primary_location": {"is_oa": false, "landing_page_url": "https://papers.nips.cc/paper/7100-excess-risk-bounds-for-the-bayes-risk-using-variational-inference-in-latent-gaussian-models.pdf", "pdf_url": null, "source": {"id": "https://openalex.org/S4363606243", "display_name": "neural information processing systems", "issn_l": null, "issn": null, "is_oa": false, "is_in_doaj": false, "host_organization": null, "host_organization_name": null, "host_organization_lineage": [], "host_organization_lineage_names": [], "type": "journal"}, "license": null, "license_id": null, "version": null, "is_accepted": false, "is_published": false}, "type": "article", "type_crossref": "proceedings-article", "indexed_in": [], "open_access": {"is_oa": false, "oa_status": "closed", "oa_url": null, "any_repository_has_fulltext": false}, "authorships": [{"author_position": "first", "author": {"id": "https://openalex.org/A5004165329", "display_name": "Rishit Sheth", "orcid": null}, "institutions": [{"id": "https://openalex.org/I121934306", "display_name": "Tufts University", "ror": "https://ror.org/05wvpxv85", "country_code": "US", "type": "education", "lineage": ["https://openalex.org/I121934306"]}], "countries": ["US"], "is_corresponding": false, "raw_author_name": "Rishit Sheth", "raw_affiliation_strings": []}, {"author_position": "last", "author": {"id": "https://openalex.org/A5013618541", "display_name": "Roni Khardon", "orcid": null}, "institutions": [{"id": "https://openalex.org/I121934306", "display_name": "Tufts University", "ror": "https://ror.org/05wvpxv85", "country_code": "US", "type": "education", "lineage": ["https://openalex.org/I121934306"]}], "countries": ["US"], "is_corresponding": false, "raw_author_name": "Roni Khardon", "raw_affiliation_strings": []}], "countries_distinct_count": 1, "institutions_distinct_count": 1, "corresponding_author_ids": [], "corresponding_institution_ids": [], "apc_list": null, "apc_paid": null, "has_fulltext": false, "cited_by_count": 17, "cited_by_percentile_year": {"min": 91, "max": 92}, "biblio": {"volume": "30", "issue": null, "first_page": "5151", "last_page": "5161"}, "is_retracted": false, "is_paratext": false, "primary_topic": {"id": "https://openalex.org/T12814", "display_name": "Gaussian Processes in Machine Learning", "score": 1.0, "subfield": {"id": "https://openalex.org/subfields/1702", "display_name": "Artificial Intelligence"}, "field": {"id": "https://openalex.org/fields/17", "display_name": "Computer Science"}, "domain": {"id": "https://openalex.org/domains/3", "display_name": "Physical Sciences"}}, "topics": [{"id": "https://openalex.org/T12814", "display_name": "Gaussian Processes in Machine Learning", "score": 1.0, "subfield": {"id": "https://openalex.org/subfields/1702", "display_name": "Artificial Intelligence"}, "field": {"id": "https://openalex.org/fields/17", "display_name": "Computer Science"}, "domain": {"id": "https://openalex.org/domains/3", "display_name": "Physical Sciences"}}, {"id": "https://openalex.org/T12072", "display_name": "Active Learning in Machine Learning Research", "score": 0.999, "subfield": {"id": "https://openalex.org/subfields/1702", "display_name": "Artificial Intelligence"}, "field": {"id": "https://openalex.org/fields/17", "display_name": "Computer Science"}, "domain": {"id": "https://openalex.org/domains/3", "display_name": "Physical Sciences"}}, {"id": "https://openalex.org/T12535", "display_name": "Learning with Noisy Labels in Machine Learning", "score": 0.9966, "subfield": {"id": "https://openalex.org/subfields/1702", "display_name": "Artificial Intelligence"}, "field": {"id": "https://openalex.org/fields/17", "display_name": "Computer Science"}, "domain": {"id": "https://openalex.org/domains/3", "display_name": "Physical Sciences"}}], "keywords": [{"id": "https://openalex.org/keywords/variational-inference", "display_name": "Variational Inference", "score": 0.559425}, {"id": "https://openalex.org/keywords/robust-learning", "display_name": "Robust Learning", "score": 0.545666}, {"id": "https://openalex.org/keywords/bayesian-inference", "display_name": "Bayesian Inference", "score": 0.542701}, {"id": "https://openalex.org/keywords/probabilistic-models", "display_name": "Probabilistic Models", "score": 0.519201}, {"id": "https://openalex.org/keywords/semi-supervised-learning", "display_name": "Semi-Supervised Learning", "score": 0.503241}], "concepts": [{"id": "https://openalex.org/C2776214188", "wikidata": "https://www.wikidata.org/wiki/Q408386", "display_name": "Inference", "level": 2, "score": 0.65546286}, {"id": "https://openalex.org/C51167844", "wikidata": "https://www.wikidata.org/wiki/Q4422623", "display_name": "Latent variable", "level": 2, "score": 0.6297833}, {"id": "https://openalex.org/C207201462", "wikidata": "https://www.wikidata.org/wiki/Q182505", "display_name": "Bayes' theorem", "level": 3, "score": 0.55483985}, {"id": "https://openalex.org/C160234255", "wikidata": "https://www.wikidata.org/wiki/Q812535", "display_name": "Bayesian inference", "level": 3, "score": 0.5536243}, {"id": "https://openalex.org/C163716315", "wikidata": "https://www.wikidata.org/wiki/Q901177", "display_name": "Gaussian", "level": 2, "score": 0.527187}, {"id": "https://openalex.org/C41008148", "wikidata": "https://www.wikidata.org/wiki/Q21198", "display_name": "Computer science", "level": 0, "score": 0.514427}, {"id": "https://openalex.org/C155846161", "wikidata": "https://www.wikidata.org/wiki/Q1143367", "display_name": "Graphical model", "level": 2, "score": 0.5021832}, {"id": "https://openalex.org/C119857082", "wikidata": "https://www.wikidata.org/wiki/Q2539", "display_name": "Machine learning", "level": 1, "score": 0.49669367}, {"id": "https://openalex.org/C107321475", "wikidata": "https://www.wikidata.org/wiki/Q5374254", "display_name": "Empirical risk minimization", "level": 2, "score": 0.48468545}, {"id": "https://openalex.org/C61224824", "wikidata": "https://www.wikidata.org/wiki/Q2260434", "display_name": "Mixture model", "level": 2, "score": 0.44113734}, {"id": "https://openalex.org/C154945302", "wikidata": "https://www.wikidata.org/wiki/Q11660", "display_name": "Artificial intelligence", "level": 1, "score": 0.4335444}, {"id": "https://openalex.org/C61326573", "wikidata": "https://www.wikidata.org/wiki/Q1496376", "display_name": "Gaussian process", "level": 3, "score": 0.42582697}, {"id": "https://openalex.org/C126255220", "wikidata": "https://www.wikidata.org/wiki/Q141495", "display_name": "Mathematical optimization", "level": 1, "score": 0.42387533}, {"id": "https://openalex.org/C107673813", "wikidata": "https://www.wikidata.org/wiki/Q812534", "display_name": "Bayesian probability", "level": 2, "score": 0.42320192}, {"id": "https://openalex.org/C11413529", "wikidata": "https://www.wikidata.org/wiki/Q8366", "display_name": "Algorithm", "level": 1, "score": 0.3950337}, {"id": "https://openalex.org/C33923547", "wikidata": "https://www.wikidata.org/wiki/Q395", "display_name": "Mathematics", "level": 0, "score": 0.38011584}, {"id": "https://openalex.org/C121332964", "wikidata": "https://www.wikidata.org/wiki/Q413", "display_name": "Physics", "level": 0, "score": 0.0}, {"id": "https://openalex.org/C62520636", "wikidata": "https://www.wikidata.org/wiki/Q944", "display_name": "Quantum mechanics", "level": 1, "score": 0.0}], "mesh": [], "locations_count": 1, "locations": [{"is_oa": false, "landing_page_url": "https://papers.nips.cc/paper/7100-excess-risk-bounds-for-the-bayes-risk-using-variational-inference-in-latent-gaussian-models.pdf", "pdf_url": null, "source": {"id": "https://openalex.org/S4363606243", "display_name": "neural information processing systems", "issn_l": null, "issn": null, "is_oa": false, "is_in_doaj": false, "host_organization": null, "host_organization_name": null, "host_organization_lineage": [], "host_organization_lineage_names": [], "type": "journal"}, "license": null, "license_id": null, "version": null, "is_accepted": false, "is_published": false}], "best_oa_location": null, "sustainable_development_goals": [], "grants": [], "referenced_works_count": 20, "referenced_works": ["https://openalex.org/W137285897", "https://openalex.org/W568673721", "https://openalex.org/W607505555", "https://openalex.org/W1516111018", "https://openalex.org/W1571870753", "https://openalex.org/W1795258949", "https://openalex.org/W2014384147", "https://openalex.org/W2060092029", "https://openalex.org/W2077723394", "https://openalex.org/W2096772472", "https://openalex.org/W2097521761", "https://openalex.org/W2099768828", "https://openalex.org/W2103972570", "https://openalex.org/W2112050062", "https://openalex.org/W2130428211", "https://openalex.org/W2165265965", "https://openalex.org/W2296319761", "https://openalex.org/W2414312348", "https://openalex.org/W2964015990", "https://openalex.org/W3120740533"], "related_works": ["https://openalex.org/W137285897", "https://openalex.org/W1859987214", "https://openalex.org/W2014384147", "https://openalex.org/W2036084078", "https://openalex.org/W2062714872", "https://openalex.org/W2099768828", "https://openalex.org/W2136097307", "https://openalex.org/W2769523825", "https://openalex.org/W2908820427", "https://openalex.org/W2962894765", "https://openalex.org/W2963303935", "https://openalex.org/W2963663068", "https://openalex.org/W2964015990", "https://openalex.org/W2994724413", "https://openalex.org/W3049347563", "https://openalex.org/W3106195168", "https://openalex.org/W3123510000", "https://openalex.org/W3168194744", "https://openalex.org/W2612481336", "https://openalex.org/W3101380508"], "ngrams_url": "https://api.openalex.org/works/W2752086744/ngrams", "abstract_inverted_index": {"Bayesian": [0, 151], "models": [1, 77, 132], "are": [2, 31, 92, 128, 143], "established": [3], "as": [4], "one": [5], "of": [6, 38, 41, 60, 74, 108, 117], "the": [7, 39, 57, 106, 109, 115, 118, 122, 150, 157, 164], "main": [8], "successful": [9], "paradigms": [10], "for": [11, 70, 86, 121], "complex": [12, 131], "problems": [13], "in": [14, 22, 130], "machine": [15], "learning.": [16], "To": [17], "handle": [18], "intractable": [19], "inference,": [20], "research": [21], "this": [23], "area": [24], "has": [25], "developed": [26], "new": [27, 167], "approximation": [28], "methods": [29], "that": [30, 153], "fast": [32], "and": [33, 64, 112, 137, 166], "effective.": [34], "However,": [35], "theoretical": [36], "analysis": [37, 52], "performance": [40], "such": [42, 51], "approximations": [43, 148], "is": [44], "not": [45, 113], "well": [46], "developed.": [47], "The": [48, 126], "paper": [49], "furthers": [50], "by": [53, 89, 145], "providing": [54], "bounds": [55, 104, 127], "on": [56, 105, 172], "excess": [58], "risk": [59, 107, 116, 158], "variational": [61, 87, 165], "inference": [62], "algorithms": [63, 69, 88, 168], "related": [65], "regularized": [66], "loss": [67], "minimization": [68], "a": [71], "large": [72], "class": [73], "latent": [75, 80], "variable": [76], "with": [78, 94], "Gaussian": [79, 135], "variables.": [81], "We": [82], "strengthen": [83], "previous": [84, 99], "results": [85, 142], "showing": [90], "they": [91], "competitive": [93], "any": [95], "point-estimate": [96], "predictor.": [97], "Unlike": [98], "work,": [100], "we": [101], "also": [102], "provide": [103], "\\emph{Bayesian}": [110], "predictor": [111, 120], "just": [114], "Gibbs": [119], "same": [123], "approximate": [124], "posterior.": [125], "applied": [129], "including": [133], "sparse": [134], "processes": [136], "correlated": [138], "topic": [139], "models.": [140], "Theoretical": [141], "complemented": [144], "identifying": [146], "novel": [147], "to": [149, 155], "objective": [152], "attempt": [154], "minimize": [156], "directly.": [159], "An": [160], "empirical": [161], "evaluation": [162], "compares": [163], "shedding": [169], "further": [170], "light": [171], "their": [173], "performance.": [174]}, "cited_by_api_url": "https://api.openalex.org/works?filter=cites:W2752086744", "counts_by_year": [{"year": 2024, "cited_by_count": 1}, {"year": 2021, "cited_by_count": 2}, {"year": 2020, "cited_by_count": 8}, {"year": 2019, "cited_by_count": 5}, {"year": 2016, "cited_by_count": 1}], "updated_date": "2024-05-01T13:41:11.880210", "created_date": "2017-09-15"}