{"id": "https://openalex.org/W2951418756", "doi": "https://doi.org/10.48550/arxiv.1905.04663", "title": "Learning to Convolve: A Generalized Weight-Tying Approach", "display_name": "Learning to Convolve: A Generalized Weight-Tying Approach", "publication_year": 2019, "publication_date": "2019-01-01", "ids": {"openalex": "https://openalex.org/W2951418756", "doi": "https://doi.org/10.48550/arxiv.1905.04663", "mag": "2951418756"}, "language": "en", "primary_location": {"is_oa": true, "landing_page_url": "https://arxiv.org/abs/1905.04663", "pdf_url": null, "source": {"id": "https://openalex.org/S4306400194", "display_name": "arXiv (Cornell University)", "issn_l": null, "issn": null, "is_oa": true, "is_in_doaj": false, "host_organization": "https://openalex.org/I205783295", "host_organization_name": "Cornell University", "host_organization_lineage": ["https://openalex.org/I205783295"], "host_organization_lineage_names": ["Cornell University"], "type": "repository"}, "license": "other-oa", "license_id": "https://openalex.org/licenses/other-oa", "version": "submittedVersion", "is_accepted": false, "is_published": false}, "type": "preprint", "type_crossref": "posted-content", "indexed_in": ["datacite"], "open_access": {"is_oa": true, "oa_status": "green", "oa_url": "https://arxiv.org/abs/1905.04663", "any_repository_has_fulltext": true}, "authorships": [{"author_position": "first", "author": {"id": "https://openalex.org/A5032611623", "display_name": "Nichita Diaconu", "orcid": null}, "institutions": [], "countries": [], "is_corresponding": false, "raw_author_name": "Nichita Diaconu", "raw_affiliation_strings": []}, {"author_position": "last", "author": {"id": "https://openalex.org/A5051011744", "display_name": "Daniel E. Worrall", "orcid": "https://orcid.org/0000-0002-9810-0709"}, "institutions": [{"id": "https://openalex.org/I887064364", "display_name": "University of Amsterdam", "ror": "https://ror.org/04dkp9463", "country_code": "NL", "type": "education", "lineage": ["https://openalex.org/I887064364"]}], "countries": ["NL"], "is_corresponding": false, "raw_author_name": "Daniel E Worrall", "raw_affiliation_strings": ["University of Amsterdam"]}], "countries_distinct_count": 1, "institutions_distinct_count": 1, "corresponding_author_ids": [], "corresponding_institution_ids": [], "apc_list": null, "apc_paid": null, "has_fulltext": false, "cited_by_count": 9, "cited_by_percentile_year": {"min": 87, "max": 88}, "biblio": {"volume": null, "issue": null, "first_page": null, "last_page": null}, "is_retracted": false, "is_paratext": false, "primary_topic": {"id": "https://openalex.org/T11307", "display_name": "Advances in Transfer Learning and Domain Adaptation", "score": 0.9998, "subfield": {"id": "https://openalex.org/subfields/1702", "display_name": "Artificial Intelligence"}, "field": {"id": "https://openalex.org/fields/17", "display_name": "Computer Science"}, "domain": {"id": "https://openalex.org/domains/3", "display_name": "Physical Sciences"}}, "topics": [{"id": "https://openalex.org/T11307", "display_name": "Advances in Transfer Learning and Domain Adaptation", "score": 0.9998, "subfield": {"id": "https://openalex.org/subfields/1702", "display_name": "Artificial Intelligence"}, "field": {"id": "https://openalex.org/fields/17", "display_name": "Computer Science"}, "domain": {"id": "https://openalex.org/domains/3", "display_name": "Physical Sciences"}}, {"id": "https://openalex.org/T11714", "display_name": "Visual Question Answering in Images and Videos", "score": 0.9995, "subfield": {"id": "https://openalex.org/subfields/1707", "display_name": "Computer Vision and Pattern Recognition"}, "field": {"id": "https://openalex.org/fields/17", "display_name": "Computer Science"}, "domain": {"id": "https://openalex.org/domains/3", "display_name": "Physical Sciences"}}, {"id": "https://openalex.org/T10627", "display_name": "Image Feature Retrieval and Recognition Techniques", "score": 0.9993, "subfield": {"id": "https://openalex.org/subfields/1707", "display_name": "Computer Vision and Pattern Recognition"}, "field": {"id": "https://openalex.org/fields/17", "display_name": "Computer Science"}, "domain": {"id": "https://openalex.org/domains/3", "display_name": "Physical Sciences"}}], "keywords": [{"id": "https://openalex.org/keywords/transfer-learning", "display_name": "Transfer Learning", "score": 0.569815}, {"id": "https://openalex.org/keywords/representation-learning", "display_name": "Representation Learning", "score": 0.556754}, {"id": "https://openalex.org/keywords/clustering-analysis", "display_name": "Clustering Analysis", "score": 0.514266}, {"id": "https://openalex.org/keywords/feature-matching", "display_name": "Feature Matching", "score": 0.510124}, {"id": "https://openalex.org/keywords/object-recognition", "display_name": "Object Recognition", "score": 0.502385}], "concepts": [{"id": "https://openalex.org/C190502265", "wikidata": "https://www.wikidata.org/wiki/Q17069496", "display_name": "MNIST database", "level": 3, "score": 0.63108134}, {"id": "https://openalex.org/C190470478", "wikidata": "https://www.wikidata.org/wiki/Q2370229", "display_name": "Invariant (physics)", "level": 2, "score": 0.5669886}, {"id": "https://openalex.org/C106131492", "wikidata": "https://www.wikidata.org/wiki/Q3072260", "display_name": "Filter (signal processing)", "level": 2, "score": 0.5624985}, {"id": "https://openalex.org/C12426560", "wikidata": "https://www.wikidata.org/wiki/Q189569", "display_name": "Basis (linear algebra)", "level": 2, "score": 0.5624028}, {"id": "https://openalex.org/C33923547", "wikidata": "https://www.wikidata.org/wiki/Q395", "display_name": "Mathematics", "level": 0, "score": 0.5008874}, {"id": "https://openalex.org/C45347329", "wikidata": "https://www.wikidata.org/wiki/Q5166604", "display_name": "Convolution (computer science)", "level": 3, "score": 0.4992447}, {"id": "https://openalex.org/C11413529", "wikidata": "https://www.wikidata.org/wiki/Q8366", "display_name": "Algorithm", "level": 1, "score": 0.470193}, {"id": "https://openalex.org/C21424316", "wikidata": "https://www.wikidata.org/wiki/Q718621", "display_name": "Chebyshev filter", "level": 2, "score": 0.46619907}, {"id": "https://openalex.org/C187691185", "wikidata": "https://www.wikidata.org/wiki/Q2020720", "display_name": "Grid", "level": 2, "score": 0.44818687}, {"id": "https://openalex.org/C2780938662", "wikidata": "https://www.wikidata.org/wiki/Q973710", "display_name": "Tying", "level": 2, "score": 0.44673818}, {"id": "https://openalex.org/C2781311116", "wikidata": "https://www.wikidata.org/wiki/Q83306", "display_name": "Group (periodic table)", "level": 2, "score": 0.4455651}, {"id": "https://openalex.org/C41008148", "wikidata": "https://www.wikidata.org/wiki/Q21198", "display_name": "Computer science", "level": 0, "score": 0.4259032}, {"id": "https://openalex.org/C74050887", "wikidata": "https://www.wikidata.org/wiki/Q848368", "display_name": "Rotation (mathematics)", "level": 2, "score": 0.42404696}, {"id": "https://openalex.org/C204241405", "wikidata": "https://www.wikidata.org/wiki/Q461499", "display_name": "Transformation (genetics)", "level": 3, "score": 0.4165303}, {"id": "https://openalex.org/C154945302", "wikidata": "https://www.wikidata.org/wiki/Q11660", "display_name": "Artificial intelligence", "level": 1, "score": 0.39409757}, {"id": "https://openalex.org/C31972630", "wikidata": "https://www.wikidata.org/wiki/Q844240", "display_name": "Computer vision", "level": 1, "score": 0.27331746}, {"id": "https://openalex.org/C108583219", "wikidata": "https://www.wikidata.org/wiki/Q197536", "display_name": "Deep learning", "level": 2, "score": 0.23945183}, {"id": "https://openalex.org/C134306372", "wikidata": "https://www.wikidata.org/wiki/Q7754", "display_name": "Mathematical analysis", "level": 1, "score": 0.23139212}, {"id": "https://openalex.org/C2524010", "wikidata": "https://www.wikidata.org/wiki/Q8087", "display_name": "Geometry", "level": 1, "score": 0.16332108}, {"id": "https://openalex.org/C50644808", "wikidata": "https://www.wikidata.org/wiki/Q192776", "display_name": "Artificial neural network", "level": 2, "score": 0.10541627}, {"id": "https://openalex.org/C111919701", "wikidata": "https://www.wikidata.org/wiki/Q9135", "display_name": "Operating system", "level": 1, "score": 0.0}, {"id": "https://openalex.org/C55493867", "wikidata": "https://www.wikidata.org/wiki/Q7094", "display_name": "Biochemistry", "level": 1, "score": 0.0}, {"id": "https://openalex.org/C185592680", "wikidata": "https://www.wikidata.org/wiki/Q2329", "display_name": "Chemistry", "level": 0, "score": 0.0}, {"id": "https://openalex.org/C178790620", "wikidata": "https://www.wikidata.org/wiki/Q11351", "display_name": "Organic chemistry", "level": 1, "score": 0.0}, {"id": "https://openalex.org/C37914503", "wikidata": "https://www.wikidata.org/wiki/Q156495", "display_name": "Mathematical physics", "level": 1, "score": 0.0}, {"id": "https://openalex.org/C104317684", "wikidata": "https://www.wikidata.org/wiki/Q7187", "display_name": "Gene", "level": 2, "score": 0.0}], "mesh": [], "locations_count": 2, "locations": [{"is_oa": true, "landing_page_url": "https://arxiv.org/abs/1905.04663", "pdf_url": null, "source": {"id": "https://openalex.org/S4306400194", "display_name": "arXiv (Cornell University)", "issn_l": null, "issn": null, "is_oa": true, "is_in_doaj": false, "host_organization": "https://openalex.org/I205783295", "host_organization_name": "Cornell University", "host_organization_lineage": ["https://openalex.org/I205783295"], "host_organization_lineage_names": ["Cornell University"], "type": "repository"}, "license": "other-oa", "license_id": "https://openalex.org/licenses/other-oa", "version": "submittedVersion", "is_accepted": false, "is_published": false}, {"is_oa": false, "landing_page_url": "https://api.datacite.org/dois/10.48550/arxiv.1905.04663", "pdf_url": null, "source": {"id": "https://openalex.org/S4393179698", "display_name": "DataCite API", "issn_l": null, "issn": null, "is_oa": true, "is_in_doaj": false, "host_organization": "https://openalex.org/I4210145204", "host_organization_name": "DataCite", "host_organization_lineage": ["https://openalex.org/I4210145204"], "host_organization_lineage_names": ["DataCite"], "type": "metadata"}, "license": null, "license_id": null, "version": null}], "best_oa_location": {"is_oa": true, "landing_page_url": "https://arxiv.org/abs/1905.04663", "pdf_url": null, "source": {"id": "https://openalex.org/S4306400194", "display_name": "arXiv (Cornell University)", "issn_l": null, "issn": null, "is_oa": true, "is_in_doaj": false, "host_organization": "https://openalex.org/I205783295", "host_organization_name": "Cornell University", "host_organization_lineage": ["https://openalex.org/I205783295"], "host_organization_lineage_names": ["Cornell University"], "type": "repository"}, "license": "other-oa", "license_id": "https://openalex.org/licenses/other-oa", "version": "submittedVersion", "is_accepted": false, "is_published": false}, "sustainable_development_goals": [], "grants": [], "referenced_works_count": 24, "referenced_works": ["https://openalex.org/W1853099646", "https://openalex.org/W1991605728", "https://openalex.org/W2117539524", "https://openalex.org/W2125186487", "https://openalex.org/W2279221249", "https://openalex.org/W2304648132", "https://openalex.org/W2340897893", "https://openalex.org/W2576915720", "https://openalex.org/W2769152880", "https://openalex.org/W2785397276", "https://openalex.org/W2785523195", "https://openalex.org/W2785994986", "https://openalex.org/W2796422723", "https://openalex.org/W2906697496", "https://openalex.org/W2963080814", "https://openalex.org/W2963107874", "https://openalex.org/W2963343946", "https://openalex.org/W2963382180", "https://openalex.org/W2963527880", "https://openalex.org/W2963703618", "https://openalex.org/W2963737468", "https://openalex.org/W2964213081", "https://openalex.org/W3037148157", "https://openalex.org/W3118608800"], "related_works": ["https://openalex.org/W4386603768", "https://openalex.org/W3046591097", "https://openalex.org/W4389249638", "https://openalex.org/W2733410219", "https://openalex.org/W2734358244", "https://openalex.org/W2950475743", "https://openalex.org/W2750384547", "https://openalex.org/W2998037107", "https://openalex.org/W2886711096", "https://openalex.org/W4380078352"], "ngrams_url": "https://api.openalex.org/works/W2951418756/ngrams", "abstract_inverted_index": {"Recent": [0], "work": [1], "(Cohen": [2], "&amp;": [3], "Welling,": [4], "2016)": [5], "has": [6], "shown": [7], "that": [8, 88], "generalizations": [9], "of": [10, 43, 87, 98], "convolutions,": [11], "based": [12], "on": [13, 52, 74, 127], "group": [14, 71], "theory,": [15], "provide": [16], "powerful": [17], "inductive": [18], "biases": [19], "for": [20, 67], "learning.": [21], "In": [22, 58], "these": [23], "generalizations,": [24], "filters": [25, 66], "are": [26, 92], "not": [27], "only": [28], "translated": [29], "but": [30], "can": [31, 113], "also": [32], "be": [33], "rotated,": [34], "flipped,": [35], "etc.": [36], "However,": [37], "coming": [38], "up": [39], "with": [40, 117], "exact": [41], "models": [42], "how": [44, 63], "to": [45, 64, 120], "rotate": [46, 103], "a": [47, 53, 80, 96, 104], "3": [48, 50], "x": [49], "filter": [51, 81, 89], "square": [54], "pixel-grid": [55], "is": [56], "difficult.": [57], "this": [59], "paper,": [60], "we": [61, 78, 106, 112], "learn": [62, 79], "transform": [65], "use": [68], "in": [69], "the": [70, 108], "convolution,": [72], "focussing": [73], "roto-translation.": [75], "For": [76], "this,": [77], "basis": [82], "and": [83, 129], "all": [84], "rotated": [85], "versions": [86], "basis.": [90, 109], "Filters": [91], "then": [93], "encoded": [94], "by": [95], "set": [97], "rotation": [99], "invariant": [100], "coefficients.": [101], "To": [102], "filter,": [105], "switch": [107], "We": [110], "demonstrate": [111], "produce": [114], "feature": [115], "maps": [116], "low": [118], "sensitivity": [119], "input": [121], "rotations,": [122], "while": [123], "achieving": [124], "high": [125], "performance": [126], "MNIST": [128], "CIFAR-10.": [130]}, "cited_by_api_url": "https://api.openalex.org/works?filter=cites:W2951418756", "counts_by_year": [{"year": 2023, "cited_by_count": 1}, {"year": 2021, "cited_by_count": 5}, {"year": 2020, "cited_by_count": 3}], "updated_date": "2024-05-09T07:02:46.307246", "created_date": "2019-06-27"}