{"id": "https://openalex.org/W2133849536", "doi": null, "title": "Learning to Rank for Personalized News Article Retrieval", "display_name": "Learning to Rank for Personalized News Article Retrieval", "publication_year": 2010, "publication_date": "2010-09-30", "ids": {"openalex": "https://openalex.org/W2133849536", "mag": "2133849536"}, "language": "en", "primary_location": {"is_oa": false, "landing_page_url": "http://proceedings.mlr.press/v11/dali10a/dali10a.pdf", "pdf_url": null, "source": null, "license": null, "license_id": null, "version": null, "is_accepted": false, "is_published": false}, "type": "article", "type_crossref": "journal-article", "indexed_in": [], "open_access": {"is_oa": false, "oa_status": "closed", "oa_url": null, "any_repository_has_fulltext": false}, "authorships": [{"author_position": "first", "author": {"id": "https://openalex.org/A5025712520", "display_name": "Lorand Dali", "orcid": null}, "institutions": [], "countries": [], "is_corresponding": false, "raw_author_name": "Lorand Dali", "raw_affiliation_strings": []}, {"author_position": "middle", "author": {"id": "https://openalex.org/A5019788602", "display_name": "Bla\u017e Fortuna", "orcid": "https://orcid.org/0000-0002-8585-9388"}, "institutions": [], "countries": [], "is_corresponding": false, "raw_author_name": "Blaz Fortuna", "raw_affiliation_strings": []}, {"author_position": "last", "author": {"id": "https://openalex.org/A5059184495", "display_name": "Jan Rupnik", "orcid": null}, "institutions": [], "countries": [], "is_corresponding": false, "raw_author_name": "Jan Rupnik", "raw_affiliation_strings": []}], "countries_distinct_count": 0, "institutions_distinct_count": 0, "corresponding_author_ids": [], "corresponding_institution_ids": [], "apc_list": null, "apc_paid": null, "has_fulltext": false, "cited_by_count": 1, "cited_by_percentile_year": {"min": 68, "max": 75}, "biblio": {"volume": null, "issue": null, "first_page": "152", "last_page": "159"}, "is_retracted": false, "is_paratext": false, "primary_topic": {"id": "https://openalex.org/T11106", "display_name": "Trajectory Data Mining and Analysis", "score": 0.9962, "subfield": {"id": "https://openalex.org/subfields/1711", "display_name": "Signal Processing"}, "field": {"id": "https://openalex.org/fields/17", "display_name": "Computer Science"}, "domain": {"id": "https://openalex.org/domains/3", "display_name": "Physical Sciences"}}, "topics": [{"id": "https://openalex.org/T11106", "display_name": "Trajectory Data Mining and Analysis", "score": 0.9962, "subfield": {"id": "https://openalex.org/subfields/1711", "display_name": "Signal Processing"}, "field": {"id": "https://openalex.org/fields/17", "display_name": "Computer Science"}, "domain": {"id": "https://openalex.org/domains/3", "display_name": "Physical Sciences"}}, {"id": "https://openalex.org/T10824", "display_name": "Shape Matching and Object Recognition", "score": 0.9958, "subfield": {"id": "https://openalex.org/subfields/1707", "display_name": "Computer Vision and Pattern Recognition"}, "field": {"id": "https://openalex.org/fields/17", "display_name": "Computer Science"}, "domain": {"id": "https://openalex.org/domains/3", "display_name": "Physical Sciences"}}, {"id": "https://openalex.org/T12016", "display_name": "Web Data Extraction and Crawling Techniques", "score": 0.9956, "subfield": {"id": "https://openalex.org/subfields/1710", "display_name": "Information Systems"}, "field": {"id": "https://openalex.org/fields/17", "display_name": "Computer Science"}, "domain": {"id": "https://openalex.org/domains/3", "display_name": "Physical Sciences"}}], "keywords": [{"id": "https://openalex.org/keywords/information-retrieval", "display_name": "Information Retrieval", "score": 0.542038}, {"id": "https://openalex.org/keywords/web-data-extraction", "display_name": "Web Data Extraction", "score": 0.527258}], "concepts": [{"id": "https://openalex.org/C189430467", "wikidata": "https://www.wikidata.org/wiki/Q7293293", "display_name": "Ranking (information retrieval)", "level": 2, "score": 0.7650785}, {"id": "https://openalex.org/C23123220", "wikidata": "https://www.wikidata.org/wiki/Q816826", "display_name": "Information retrieval", "level": 1, "score": 0.70157635}, {"id": "https://openalex.org/C41008148", "wikidata": "https://www.wikidata.org/wiki/Q21198", "display_name": "Computer science", "level": 0, "score": 0.68971455}, {"id": "https://openalex.org/C93518851", "wikidata": "https://www.wikidata.org/wiki/Q180160", "display_name": "Metadata", "level": 2, "score": 0.65815043}, {"id": "https://openalex.org/C192209626", "wikidata": "https://www.wikidata.org/wiki/Q190909", "display_name": "Focus (optics)", "level": 2, "score": 0.65568274}, {"id": "https://openalex.org/C164226766", "wikidata": "https://www.wikidata.org/wiki/Q7293202", "display_name": "Rank (graph theory)", "level": 2, "score": 0.5919601}, {"id": "https://openalex.org/C201280247", "wikidata": "https://www.wikidata.org/wiki/Q11032", "display_name": "Newspaper", "level": 2, "score": 0.58854574}, {"id": "https://openalex.org/C2776945383", "wikidata": "https://www.wikidata.org/wiki/Q7170667", "display_name": "Personalized search", "level": 3, "score": 0.5705274}, {"id": "https://openalex.org/C136764020", "wikidata": "https://www.wikidata.org/wiki/Q466", "display_name": "World Wide Web", "level": 1, "score": 0.5324277}, {"id": "https://openalex.org/C86037889", "wikidata": "https://www.wikidata.org/wiki/Q4330127", "display_name": "Learning to rank", "level": 3, "score": 0.47569072}, {"id": "https://openalex.org/C97854310", "wikidata": "https://www.wikidata.org/wiki/Q19541", "display_name": "Search engine", "level": 2, "score": 0.18801284}, {"id": "https://openalex.org/C112698675", "wikidata": "https://www.wikidata.org/wiki/Q37038", "display_name": "Advertising", "level": 1, "score": 0.12492114}, {"id": "https://openalex.org/C33923547", "wikidata": "https://www.wikidata.org/wiki/Q395", "display_name": "Mathematics", "level": 0, "score": 0.06538573}, {"id": "https://openalex.org/C121332964", "wikidata": "https://www.wikidata.org/wiki/Q413", "display_name": "Physics", "level": 0, "score": 0.0}, {"id": "https://openalex.org/C114614502", "wikidata": "https://www.wikidata.org/wiki/Q76592", "display_name": "Combinatorics", "level": 1, "score": 0.0}, {"id": "https://openalex.org/C120665830", "wikidata": "https://www.wikidata.org/wiki/Q14620", "display_name": "Optics", "level": 1, "score": 0.0}, {"id": "https://openalex.org/C144133560", "wikidata": "https://www.wikidata.org/wiki/Q4830453", "display_name": "Business", "level": 0, "score": 0.0}], "mesh": [], "locations_count": 1, "locations": [{"is_oa": false, "landing_page_url": "http://proceedings.mlr.press/v11/dali10a/dali10a.pdf", "pdf_url": null, "source": null, "license": null, "license_id": null, "version": null, "is_accepted": false, "is_published": false}], "best_oa_location": null, "sustainable_development_goals": [{"id": "https://metadata.un.org/sdg/1", "display_name": "No poverty", "score": 0.55}], "grants": [], "datasets": [], "versions": [], "referenced_works_count": 20, "referenced_works": ["https://openalex.org/W1042576697", "https://openalex.org/W1482214997", "https://openalex.org/W1510348757", "https://openalex.org/W1538832911", "https://openalex.org/W1546928902", "https://openalex.org/W1576520375", "https://openalex.org/W1604938182", "https://openalex.org/W1995386266", "https://openalex.org/W2040870580", "https://openalex.org/W2047221353", "https://openalex.org/W2071106922", "https://openalex.org/W2080950999", "https://openalex.org/W2104598215", "https://openalex.org/W2113762394", "https://openalex.org/W2123427850", "https://openalex.org/W2127203709", "https://openalex.org/W2131295015", "https://openalex.org/W2169223373", "https://openalex.org/W2752186376", "https://openalex.org/W3184997840"], "related_works": ["https://openalex.org/W996170008", "https://openalex.org/W3181809832", "https://openalex.org/W3093729421", "https://openalex.org/W3088971166", "https://openalex.org/W3023990848", "https://openalex.org/W2969483045", "https://openalex.org/W2962106431", "https://openalex.org/W2953222773", "https://openalex.org/W2929958937", "https://openalex.org/W2777794638", "https://openalex.org/W2599558711", "https://openalex.org/W2593014441", "https://openalex.org/W2475412399", "https://openalex.org/W2378522053", "https://openalex.org/W2182189109", "https://openalex.org/W2139395386", "https://openalex.org/W2119541122", "https://openalex.org/W2027289847", "https://openalex.org/W2018515916", "https://openalex.org/W1995246960"], "ngrams_url": "https://api.openalex.org/works/W2133849536/ngrams", "abstract_inverted_index": {"This": [0], "paper": [1], "aims": [2], "to": [3, 64, 89], "tackle": [4], "the": [5, 25, 29, 65, 77, 84, 90], "very": [6], "interesting": [7], "and": [8, 24, 58], "important": [9], "problem": [10], "of": [11, 15], "user": [12, 66, 78, 85], "personalized": [13, 42], "ranking": [14, 30, 45], "search": [16, 44], "results.": [17], "The": [18, 41], "focus": [19], "is": [20, 32, 81], "on": [21], "news": [22, 43, 91], "retrieval": [23], "data": [26, 62, 80], "from": [27], "which": [28, 47], "model": [31, 46], "learned": [33], "was": [34], "provided": [35, 82], "by": [36, 83], "a": [37], "large": [38], "online": [39], "newspaper.": [40], "we": [48], "have": [49], "developed": [50], "takes": [51], "into": [52], "account": [53], "not": [54], "only": [55], "document": [56], "content": [57], "metadata,": [59], "but": [60], "also": [61], "specic": [63, 79], "such": [67], "as": [68], "age,": [69], "gender,": [70], "job,": [71], "income,": [72], "city,": [73], "country": [74], "etc.": [75], "All": [76], "himself": [86], "when": [87], "registering": [88], "site.": [92]}, "cited_by_api_url": "https://api.openalex.org/works?filter=cites:W2133849536", "counts_by_year": [{"year": 2017, "cited_by_count": 1}], "updated_date": "2024-05-10T05:15:23.718142", "created_date": "2016-06-24"}