{"id": "https://openalex.org/W2112380340", "doi": null, "title": "Privacy-preserving logistic regression", "display_name": "Privacy-preserving logistic regression", "publication_year": 2008, "publication_date": "2008-12-08", "ids": {"openalex": "https://openalex.org/W2112380340", "mag": "2112380340"}, "language": "en", "primary_location": {"is_oa": false, "landing_page_url": "http://books.nips.cc/papers/files/nips21/NIPS2008_0964.pdf", "pdf_url": null, "source": {"id": "https://openalex.org/S4363606243", "display_name": "neural information processing systems", "issn_l": null, "issn": null, "is_oa": false, "is_in_doaj": false, "host_organization": null, "host_organization_name": null, "host_organization_lineage": [], "host_organization_lineage_names": [], "type": "journal"}, "license": null, "license_id": null, "version": null, "is_accepted": false, "is_published": false}, "type": "article", "type_crossref": "proceedings-article", "indexed_in": [], "open_access": {"is_oa": false, "oa_status": "closed", "oa_url": null, "any_repository_has_fulltext": false}, "authorships": [{"author_position": "first", "author": {"id": "https://openalex.org/A5010790447", "display_name": "Kamalika Chaudhuri", "orcid": null}, "institutions": [{"id": "https://openalex.org/I36258959", "display_name": "University of California, San Diego", "ror": "https://ror.org/0168r3w48", "country_code": "US", "type": "education", "lineage": ["https://openalex.org/I2803209242", "https://openalex.org/I36258959"]}], "countries": ["US"], "is_corresponding": false, "raw_author_name": "Kamalika Chaudhuri", "raw_affiliation_strings": ["Information Theory and Applications, University of California, San Diego#TAB#"]}, {"author_position": "last", "author": {"id": "https://openalex.org/A5001457347", "display_name": "Claire Monteleoni", "orcid": null}, "institutions": [{"id": "https://openalex.org/I78577930", "display_name": "Columbia University", "ror": "https://ror.org/00hj8s172", "country_code": "US", "type": "education", "lineage": ["https://openalex.org/I78577930"]}], "countries": ["US"], "is_corresponding": false, "raw_author_name": "Claire Monteleoni", "raw_affiliation_strings": ["Center for Computational Learning Systems, Columbia University,"]}], "countries_distinct_count": 1, "institutions_distinct_count": 2, "corresponding_author_ids": [], "corresponding_institution_ids": [], "apc_list": null, "apc_paid": null, "has_fulltext": false, "cited_by_count": 326, "cited_by_percentile_year": {"min": 99, "max": 100}, "biblio": {"volume": "21", "issue": null, "first_page": "289", "last_page": "296"}, "is_retracted": false, "is_paratext": false, "primary_topic": {"id": "https://openalex.org/T10764", "display_name": "Privacy-Preserving Techniques for Data Analysis and Machine Learning", "score": 1.0, "subfield": {"id": "https://openalex.org/subfields/1702", "display_name": "Artificial Intelligence"}, "field": {"id": "https://openalex.org/fields/17", "display_name": "Computer Science"}, "domain": {"id": "https://openalex.org/domains/3", "display_name": "Physical Sciences"}}, "topics": [{"id": "https://openalex.org/T10764", "display_name": "Privacy-Preserving Techniques for Data Analysis and Machine Learning", "score": 1.0, "subfield": {"id": "https://openalex.org/subfields/1702", "display_name": "Artificial Intelligence"}, "field": {"id": "https://openalex.org/fields/17", "display_name": "Computer Science"}, "domain": {"id": "https://openalex.org/domains/3", "display_name": "Physical Sciences"}}, {"id": "https://openalex.org/T11704", "display_name": "Crowdsourcing for Research and Data Collection", "score": 0.9802, "subfield": {"id": "https://openalex.org/subfields/1706", "display_name": "Computer Science Applications"}, "field": {"id": "https://openalex.org/fields/17", "display_name": "Computer Science"}, "domain": {"id": "https://openalex.org/domains/3", "display_name": "Physical Sciences"}}, {"id": "https://openalex.org/T11612", "display_name": "Optimization Methods in Machine Learning", "score": 0.9792, "subfield": {"id": "https://openalex.org/subfields/1702", "display_name": "Artificial Intelligence"}, "field": {"id": "https://openalex.org/fields/17", "display_name": "Computer Science"}, "domain": {"id": "https://openalex.org/domains/3", "display_name": "Physical Sciences"}}], "keywords": [{"id": "https://openalex.org/keywords/location-privacy", "display_name": "Location Privacy", "score": 0.558065}, {"id": "https://openalex.org/keywords/differential-privacy", "display_name": "Differential Privacy", "score": 0.543639}, {"id": "https://openalex.org/keywords/privacy-preservation", "display_name": "Privacy Preservation", "score": 0.524844}, {"id": "https://openalex.org/keywords/large-scale-optimization", "display_name": "Large-Scale Optimization", "score": 0.511442}, {"id": "https://openalex.org/keywords/approximation-algorithms", "display_name": "Approximation Algorithms", "score": 0.502978}], "concepts": [{"id": "https://openalex.org/C151956035", "wikidata": "https://www.wikidata.org/wiki/Q1132755", "display_name": "Logistic regression", "level": 2, "score": 0.7588272}, {"id": "https://openalex.org/C23130292", "wikidata": "https://www.wikidata.org/wiki/Q5275358", "display_name": "Differential privacy", "level": 2, "score": 0.7078165}, {"id": "https://openalex.org/C41008148", "wikidata": "https://www.wikidata.org/wiki/Q21198", "display_name": "Computer science", "level": 0, "score": 0.6482641}, {"id": "https://openalex.org/C63584917", "wikidata": "https://www.wikidata.org/wiki/Q333286", "display_name": "Bounding overwatch", "level": 2, "score": 0.60787594}, {"id": "https://openalex.org/C61722155", "wikidata": "https://www.wikidata.org/wiki/Q6667643", "display_name": "Logistic model tree", "level": 3, "score": 0.55537283}, {"id": "https://openalex.org/C154945302", "wikidata": "https://www.wikidata.org/wiki/Q11660", "display_name": "Artificial intelligence", "level": 1, "score": 0.48681948}, {"id": "https://openalex.org/C119857082", "wikidata": "https://www.wikidata.org/wiki/Q2539", "display_name": "Machine learning", "level": 1, "score": 0.45277742}, {"id": "https://openalex.org/C123201435", "wikidata": "https://www.wikidata.org/wiki/Q456632", "display_name": "Information privacy", "level": 2, "score": 0.4494422}, {"id": "https://openalex.org/C21200559", "wikidata": "https://www.wikidata.org/wiki/Q7451068", "display_name": "Sensitivity (control systems)", "level": 2, "score": 0.44641012}, {"id": "https://openalex.org/C95623464", "wikidata": "https://www.wikidata.org/wiki/Q1096149", "display_name": "Classifier (UML)", "level": 2, "score": 0.4368522}, {"id": "https://openalex.org/C11413529", "wikidata": "https://www.wikidata.org/wiki/Q8366", "display_name": "Algorithm", "level": 1, "score": 0.4043811}, {"id": "https://openalex.org/C124101348", "wikidata": "https://www.wikidata.org/wiki/Q172491", "display_name": "Data mining", "level": 1, "score": 0.3257951}, {"id": "https://openalex.org/C38652104", "wikidata": "https://www.wikidata.org/wiki/Q3510521", "display_name": "Computer security", "level": 1, "score": 0.073437154}, {"id": "https://openalex.org/C24326235", "wikidata": "https://www.wikidata.org/wiki/Q126095", "display_name": "Electronic engineering", "level": 1, "score": 0.0}, {"id": "https://openalex.org/C127413603", "wikidata": "https://www.wikidata.org/wiki/Q11023", "display_name": "Engineering", "level": 0, "score": 0.0}], "mesh": [], "locations_count": 1, "locations": [{"is_oa": false, "landing_page_url": "http://books.nips.cc/papers/files/nips21/NIPS2008_0964.pdf", "pdf_url": null, "source": {"id": "https://openalex.org/S4363606243", "display_name": "neural information processing systems", "issn_l": null, "issn": null, "is_oa": false, "is_in_doaj": false, "host_organization": null, "host_organization_name": null, "host_organization_lineage": [], "host_organization_lineage_names": [], "type": "journal"}, "license": null, "license_id": null, "version": null, "is_accepted": false, "is_published": false}], "best_oa_location": null, "sustainable_development_goals": [], "grants": [], "referenced_works_count": 17, "referenced_works": ["https://openalex.org/W56293434", "https://openalex.org/W1873763122", "https://openalex.org/W1993116423", "https://openalex.org/W2030811966", "https://openalex.org/W2097272254", "https://openalex.org/W2101771965", "https://openalex.org/W2114609025", "https://openalex.org/W2120456162", "https://openalex.org/W2123224804", "https://openalex.org/W2123733729", "https://openalex.org/W2128906841", "https://openalex.org/W2130099852", "https://openalex.org/W2134167315", "https://openalex.org/W2134479759", "https://openalex.org/W2135930857", "https://openalex.org/W2169570643", "https://openalex.org/W2911978475"], "related_works": ["https://openalex.org/W1557833142", "https://openalex.org/W1873763122", "https://openalex.org/W1985511977", "https://openalex.org/W1992926795", "https://openalex.org/W1993116423", "https://openalex.org/W2010523825", "https://openalex.org/W2027595342", "https://openalex.org/W2053637704", "https://openalex.org/W2096633407", "https://openalex.org/W2101771965", "https://openalex.org/W2109135024", "https://openalex.org/W2109426455", "https://openalex.org/W2119874464", "https://openalex.org/W2138865266", "https://openalex.org/W2159024459", "https://openalex.org/W2162379889", "https://openalex.org/W2167372639", "https://openalex.org/W2473418344", "https://openalex.org/W2535690855", "https://openalex.org/W2911978475"], "ngrams_url": "https://api.openalex.org/works/W2112380340/ngrams", "abstract_inverted_index": {"This": [0, 41], "paper": [1], "addresses": [2], "the": [3, 44, 52, 59, 88, 126, 136, 139], "important": [4], "tradeoff": [5], "between": [6, 158], "privacy": [7, 86], "and": [8, 50, 141, 160], "learnability,": [9], "when": [10], "designing": [11], "algorithms": [12], "for": [13, 97, 103], "learning": [14, 95, 120], "from": [15], "private": [16], "databases.": [17], "We": [18, 80, 93], "focus": [19], "on": [20, 70, 135], "privacy-preserving": [21, 37, 64, 73, 130], "logistic": [22, 38, 48, 66, 115], "regression.": [23, 116], "First": [24], "we": [25], "apply": [26, 114], "an": [27, 155], "idea": [28], "of": [29, 46, 122, 138, 147], "Dwork": [30], "et": [31], "al.": [32], "[6]": [33], "to": [34, 58, 91, 144], "design": [35], "a": [36, 63, 71, 76, 145], "regression": [39, 67], "algorithm.": [40], "involves": [42], "bounding": [43], "sensitivity": [45, 127, 137], "regularized": [47, 65], "regression,": [49], "perturbing": [51], "learned": [53], "classifier": [54], "with": [55], "noise": [56], "proportional": [57], "sensitivity.\r\n\r\nWe": [60], "then": [61], "provide": [62, 94], "algorithm": [68, 84], "based": [69], "new": [72, 105], "technique:": [74], "solving": [75], "perturbed": [77], "optimization": [78], "problem.": [79], "prove": [81], "that": [82], "our": [83, 104, 123], "preserves": [85], "in": [87, 107, 109], "model": [89], "due": [90], "[6].": [92], "guarantees": [96], "both": [98], "algorithms,": [99], "which": [100, 110], "are": [101], "tighter": [102], "algorithm,": [106], "cases": [108], "one": [111], "would": [112], "typically": [113], "Experiments": [117], "demonstrate": [118], "improved": [119], "performance": [121], "method,": [124], "versus": [125], "method.": [128], "Our": [129, 151], "technique": [131], "does": [132], "not": [133], "depend": [134], "function,": [140], "extends": [142], "easily": [143], "class": [146], "convex": [148], "loss": [149], "functions.": [150], "work": [152], "also": [153], "reveals": [154], "interesting": [156], "connection": [157], "regularization": [159], "privacy.": [161]}, "cited_by_api_url": "https://api.openalex.org/works?filter=cites:W2112380340", "counts_by_year": [{"year": 2024, "cited_by_count": 2}, {"year": 2023, "cited_by_count": 10}, {"year": 2022, "cited_by_count": 5}, {"year": 2021, "cited_by_count": 42}, {"year": 2020, "cited_by_count": 51}, {"year": 2019, "cited_by_count": 53}, {"year": 2018, "cited_by_count": 34}, {"year": 2017, "cited_by_count": 25}, {"year": 2016, "cited_by_count": 23}, {"year": 2015, "cited_by_count": 22}, {"year": 2014, "cited_by_count": 14}, {"year": 2013, "cited_by_count": 10}, {"year": 2012, "cited_by_count": 11}], "updated_date": "2024-05-01T05:30:01.519106", "created_date": "2016-06-24"}